crimm/Fetchers.py
crimm/__init__.py
crimm/Adaptors/OMMAdaptors.py
crimm/Adaptors/OpenBabelAdaptors.py
crimm/Adaptors/PropKaAdaptors.py
crimm/Adaptors/RDKitConverter.py
crimm/Adaptors/__init__.py
crimm/Adaptors/charmm_struct_prep.py
crimm/Adaptors/pyCHARMMAdaptors.py
crimm/Data/__init__.py
crimm/Data/cgenff_mass_dict.py
crimm/Data/components_dict.py
crimm/Data/connect_records.py
crimm/Data/constants.py
crimm/Data/element_dict.py
crimm/Data/propka.cfg
crimm/Data/ptable.py
crimm/Data/water_coords.npy
crimm/Data/probes/__init__.py
crimm/Data/probes/probes.py
crimm/Data/toppar/carb.prm
crimm/Data/toppar/carb.rtf
crimm/Data/toppar/carb_glycopeptide.prm
crimm/Data/toppar/carb_glycopeptide.rtf
crimm/Data/toppar/cgenff.prm
crimm/Data/toppar/cgenff.rtf
crimm/Data/toppar/ethers.prm
crimm/Data/toppar/ethers.rtf
crimm/Data/toppar/label_fluorophore.prm
crimm/Data/toppar/label_fluorophore.rtf
crimm/Data/toppar/label_spin.prm
crimm/Data/toppar/label_spin.rtf
crimm/Data/toppar/lipid.prm
crimm/Data/toppar/lipid.rtf
crimm/Data/toppar/lipid_cholesterol.prm
crimm/Data/toppar/lipid_cholesterol.rtf
crimm/Data/toppar/lipid_sphingo.prm
crimm/Data/toppar/lipid_sphingo.rtf
crimm/Data/toppar/moreions.prm
crimm/Data/toppar/moreions.rtf
crimm/Data/toppar/na.prm
crimm/Data/toppar/na.rtf
crimm/Data/toppar/na_rna_modified.prm
crimm/Data/toppar/na_rna_modified.rtf
crimm/Data/toppar/polymer_solvent.prm
crimm/Data/toppar/polymer_solvent.rtf
crimm/Data/toppar/prot.prm
crimm/Data/toppar/prot.rtf
crimm/Data/toppar/prot_heme.prm
crimm/Data/toppar/prot_heme.rtf
crimm/Data/toppar/prot_modify_res.prm
crimm/Data/toppar/prot_modify_res.rtf
crimm/Data/toppar/synthetic_polymer.prm
crimm/Data/toppar/synthetic_polymer.rtf
crimm/Data/toppar/water_ions.prm
crimm/Data/toppar/water_ions.rtf
crimm/Data/toppar/water_ions.str
crimm/IO/CRDParser.py
crimm/IO/CRDWriter.py
crimm/IO/MMCIF2Dict.py
crimm/IO/MMCIFParser.py
crimm/IO/PDBParser.py
crimm/IO/PDBString.py
crimm/IO/PRMParser.py
crimm/IO/PSFReader.py
crimm-2026.1.1.dist-info/licenses/LICENSE
crimm-2026.1.1.dist-info/METADATA
crimm-2026.1.1.dist-info/WHEEL
crimm-2026.1.1.dist-info/top_level.txt
crimm-2026.1.1.dist-info/RECORD
