Metadata-Version: 2.4
Name: crimm
Version: 2026.1.1
Summary: Chemistry with the ReInvented Macromolecular Mechanics
Author-email: Truman Xu <ziqiaoxu@umich.edu>, Stanislav Cherepanov <stanislc@umich.edu>
License: GPL-3.0-or-later
Project-URL: Homepage, https://github.com/BrooksResearchGroup-UM/crimm
Project-URL: Bug Tracker, https://github.com/BrooksResearchGroup-UM/crimm/issues
Classifier: Programming Language :: Python :: 3
Classifier: License :: OSI Approved :: GNU General Public License v3 (GPLv3)
Classifier: Operating System :: OS Independent
Classifier: Development Status :: 2 - Pre-Alpha
Requires-Python: >=3.9
License-File: LICENSE
Requires-Dist: numpy>=1.24
Requires-Dist: biopython>=1.80
Requires-Dist: ipywidgets>=8
Requires-Dist: nglview>=3.1
Requires-Dist: scipy>=1.10
Requires-Dist: requests>=2.28
Requires-Dist: pandas>=1.5
Provides-Extra: protonation
Requires-Dist: propka>=3.5.1; extra == "protonation"
Provides-Extra: cheminformatics
Requires-Dist: rdkit; extra == "cheminformatics"
Provides-Extra: all
Requires-Dist: propka>=3.5.1; extra == "all"
Requires-Dist: rdkit; extra == "all"
Dynamic: license-file
